tmplayer/__init__.py
tmplayer/main.py
tmplayer/player.py
tmplayer/ui.py
tmplayer/version.py
tmplayer-0.0.5.dist-info/LICENSE
tmplayer-0.0.5.dist-info/METADATA
tmplayer-0.0.5.dist-info/WHEEL
tmplayer-0.0.5.dist-info/entry_points.txt
tmplayer-0.0.5.dist-info/top_level.txt
tmplayer-0.0.5.dist-info/RECORD
