Metadata-Version: 2.1
Name: tmplayer
Version: 0.0.5
Summary: Minimalist music player for audio files with a pleasant UI.
Author: Piotr Skowroński
License: MIT
Classifier: Topic :: Multimedia :: Sound/Audio
Classifier: Environment :: Console
Classifier: Operating System :: POSIX
Classifier: Programming Language :: Python :: 3
Classifier: License :: OSI Approved :: MIT License
Requires-Python: >=3.10
License-File: LICENSE
Requires-Dist: urwid (>=2.1.2)
Requires-Dist: python-vlc (>=3.0.18121)
Provides-Extra: formatting
Requires-Dist: black ; extra == 'formatting'
Provides-Extra: linting
Requires-Dist: flake8 ; extra == 'linting'
Requires-Dist: mypy ; extra == 'linting'
